{
  "target_repo": {
    "url": "https://github.com/MicrosoftDocs/azure-docs-sdk-node",
    "branch": "smoke-test",
    "folder": "preview-packages"
  },
  "npm_package_sources": [
    {
      "name": "@azure/schema-registry-avro@1.0.0-alpha.20220210.1"
    },
    {
      "name": "@azure/identity@2.0.0-beta.6"
    },
    {
      "name": "@azure/monitor-opentelemetry-exporter@1.0.0-alpha.20220210.1"
    },
    {
      "name": "@azure/amqp-common@next"
    },
    {
      "name": "@azure/digital-twins@next"
    },
    {
      "name": "@azure/opentelemetry-exporter-azure-monitor@next"
    },
    {
      "name": "@azure/core-https"
    },
    {
      "name": "@azure/quantum-jobs@next"
    },
    {
      "name": "@azure/template@1.0.12-beta.1346472"
    },
    {
      "name": "@azure/arm-appservice@10.0.0-beta.1"
    },
    {
      "name": "@azure-rest/purview-account@1.0.0-beta.1"
    },
    {
      "name": "@azure/arm-eventhub@5.0.0-beta.1"
    },
    {
      "name": "@azure/arm-servicebus@5.0.0-beta.1"
    },
    {
      "name": "@azure/mixed-reality-authentication@1.0.0-beta.1"
    },
    {
      "name": "@azure/service-bus@7.4.0-beta.1"
    },
    {
      "name": "@azure/arm-eventgrid@13.0.0-beta.1"
    },
    {
      "name": "@azure/arm-appplatform@2.0.0-beta.2"
    },
    {
      "name": "@azure/event-hubs@5.8.0-beta.1"
    },
    {
      "name": "@azure/arm-loadtestservice@1.0.0-beta.1"
    },
    {
      "name": "@azure/arm-kubernetesconfiguration@5.0.0-beta.1"
    },
    {
      "name": "@azure/arm-hanaonazure@4.0.0-beta.1"
    },
    {
      "name": "@azure/arm-deploymentmanager@4.0.0-beta.2"
    },
    {
      "name": "@azure/arm-labservices@3.0.0-beta.1"
    },
    {
      "name": "@azure/arm-appinsights@5.0.0-alpha.20220210.1"
    },
    {
      "name": "@azure/arm-servicefabricmesh@3.0.0-beta.1"
    },
    {
      "name": "@azure-rest/core-client-paging@1.0.0-beta.1"
    },
    {
      "name": "@azure/core-http@2.2.5-alpha.20220210.2"
    },
    {
      "name": "@azure/core-rest-pipeline@1.5.1-alpha.20220210.2"
    }
  ],
  "source_repos": []
}
